<?xml version="1.0" encoding="UTF-8" ?>
<QUITEXML xmlns="http://www.quite.com/general/ns/quitexml/">
<ITEMS>
<DICT N='0'>  <ITEMS>
  <A N='Category'>OneCommand_V1</A>
  <A N='Command'>InsertBlanks</A>
  <DICT N='Desc'>    <ITEMS>
    <S N='0'>Where: before first page</S>
    <S N='1'>Number of pages: 1</S>
    <S N='2'>Page size: same as page 1</S>
    </ITEMS>  </DICT>

  <DICT N='Params'>    <ITEMS>
    <A N='Action'>Blanks</A>
    <A N='Condition'>Always</A>
    <I N='Count'>1</I>
    <I N='PageNum'>1</I>
    <I N='PosX'>1035</I>
    <I N='PosY'>400</I>
    <B N='Repeat'>0</B>
    <I N='RepeatInterval'>1</I>
    <S N='Requires'>qi3alphabase[QI 3.0/QHI 3.0 alpha]</S>
    <I N='SizeAsPage'>1</I>
    <DICT N='Source'>      <ITEMS>
      <A N='SourceType'>None</A>
      </ITEMS>    </DICT>

    <A N='WhatSize'>SameAsPage</A>
    <A N='Where'>AtStart</A>
    </ITEMS>  </DICT>

  <DICT N='Provider'>    <ITEMS>
    <S N='Code'>QITE_QuiteImposingPlus5</S>
    <S N='FullName'>Quite Imposing Plus 5.2</S>
    <S N='Name'>Quite Imposing Plus 5</S>
    <I N='Version'>1</I>
    </ITEMS>  </DICT>

  <I N='Version'>1</I>
  </ITEMS></DICT>

<DICT N='1'>  <ITEMS>
  <A N='Category'>OneCommand_V1</A>
  <A N='Command'>InsertBlanks</A>
  <DICT N='Desc'>    <ITEMS>
    <S N='0'>Where: after page 5</S>
    <S N='1'>Number of pages: 1</S>
    <S N='2'>Page size: same as page 1</S>
    </ITEMS>  </DICT>

  <DICT N='Params'>    <ITEMS>
    <A N='Action'>Blanks</A>
    <A N='Condition'>Always</A>
    <I N='Count'>1</I>
    <I N='PageNum'>5</I>
    <I N='PosX'>1035</I>
    <I N='PosY'>400</I>
    <B N='Repeat'>0</B>
    <I N='RepeatInterval'>1</I>
    <S N='Requires'>qi3alphabase[QI 3.0/QHI 3.0 alpha]</S>
    <I N='SizeAsPage'>1</I>
    <DICT N='Source'>      <ITEMS>
      <A N='SourceType'>None</A>
      </ITEMS>    </DICT>

    <A N='WhatSize'>SameAsPage</A>
    <A N='Where'>AfterNum</A>
    </ITEMS>  </DICT>

  <DICT N='Provider'>    <ITEMS>
    <S N='Code'>QITE_QuiteImposingPlus5</S>
    <S N='FullName'>Quite Imposing Plus 5.2</S>
    <S N='Name'>Quite Imposing Plus 5</S>
    <I N='Version'>1</I>
    </ITEMS>  </DICT>

  <I N='Version'>1</I>
  </ITEMS></DICT>

<DICT N='2'>  <ITEMS>
  <A N='Category'>OneCommand_V1</A>
  <A N='Command'>PageTools</A>
  <DICT N='Desc'>    <ITEMS>
    <S N='0'>Action: Duplicate pages</S>
    <S N='1'>Range: all pages</S>
    <S N='2'>Copies: 2</S>
    <S N='3'>Collate: yes</S>
    </ITEMS>  </DICT>

  <DICT N='Params'>    <ITEMS>
    <A N='Action'>DuplicatePages</A>
    <B N='Collate'>1</B>
    <I N='Copies'>2</I>
    <I N='PosX'>747</I>
    <I N='PosY'>322</I>
    <S N='Requires'>qi3alphabase[QI 3.0/QHI 3.0 alpha]</S>
    <DICT N='Source'>      <ITEMS>
      <DICT N='Range'>        <ITEMS>
        <A N='RangeType'>AllDoc</A>
        </ITEMS>      </DICT>

      </ITEMS>    </DICT>

    </ITEMS>  </DICT>

  <DICT N='Provider'>    <ITEMS>
    <S N='Code'>QITE_QuiteImposingPlus3</S>
    <S N='FullName'>Quite Imposing Plus 3.0f</S>
    <S N='Name'>Quite Imposing Plus 3</S>
    <I N='Version'>1</I>
    </ITEMS>  </DICT>

  <I N='Version'>1</I>
  </ITEMS></DICT>

<DICT N='3'>  <ITEMS>
  <A N='Category'>OneCommand_V1</A>
  <A N='Command'>Nup</A>
  <DICT N='Desc'>    <ITEMS>
    <S N='0'>Trim unused space from sheets: no</S>
    <S N='1'>Allow pages to be scaled: no</S>
    <S N='2'>Margins: left 0.00, top 0.00, right 0.00, bottom 0.00 points</S>
    <S N='3'>Horizontal spacing (points): 0 </S>
    <S N='4'>Vertical spacing (points): 0 </S>
    <S N='5'>Add frames around each page: no</S>
    <S N='6'>Sheet size: 1.000 x 1.000 inches / 25.4 x 25.4 mm</S>
    <S N='7'>Sheet orientation: tall</S>
    <S N='8'>Layout: rows 1 down, columns 1 across</S>
    <S N='9'>Align: centre, independent</S>
    <S N='10'>Registration colour: All separations</S>
    <S N='11'>PDF/X handling: Ignore PDF/X</S>
    <S N='12'>Bleed handling: Use trim box</S>
    <S N='13'>Annotations and form fields: Ignore</S>
    </ITEMS>  </DICT>

  <DICT N='Params'>    <ITEMS>
    <F N='BMgn'>0.0000</F>
    <A N='BleedMode'>Use</A>
    <F N='CropDist'>10.0000</F>
    <F N='CropLength'>20.0000</F>
    <B N='CropMarks'>0</B>
    <A N='CropStyle'>Corners</A>
    <F N='CropWidth'>0.3000</F>
    <A N='DoScaling'>ToFit</A>
    <B N='EvenMirrorHorizontal'>0</B>
    <B N='EvenMirrorVertical'>0</B>
    <I N='FitAcross'>1</I>
    <I N='FitDown'>1</I>
    <F N='FixedScale'>0.7000</F>
    <A N='Flatten'>None</A>
    <B N='Frames'>0</B>
    <S N='HSpace'>0 </S>
    <F N='LMgn'>0.0000</F>
    <B N='NewDoc'>0</B>
    <A N='PDFX'>IgnoreAll</A>
    <DICT N='Page'>      <ITEMS>
      <S N='Created'>D:20200808222810</S>
      <F N='Height'>72.0000</F>
      <S N='Name'>SI2P</S>
      <A N='Type'>Blank</A>
      <F N='Width'>69.4488</F>
      </ITEMS>    </DICT>

    <A N='PageOrientation'>Tall</A>
    <I N='PosX'>749</I>
    <I N='PosY'>303</I>
    <F N='RMgn'>0.0000</F>
    <A N='RegColour'>AllSeps</A>
    <A N='SheetAlign'>C</A>
    <B N='SheetAlignIndependent'>1</B>
    <DICT N='Source'>      <ITEMS>
      <A N='SourceType'>CurrentAVDoc</A>
      </ITEMS>    </DICT>

    <F N='TMgn'>0.0000</F>
    <B N='Trim'>0</B>
    <I N='UIVer'>2</I>
    <B N='UseMgn'>1</B>
    <B N='UseScale'>0</B>
    <S N='VSpace'>0 </S>
    </ITEMS>  </DICT>

  <DICT N='Provider'>    <ITEMS>
    <S N='Code'>QITE_QuiteImposingPlus3</S>
    <S N='FullName'>Quite Imposing Plus 3.0f</S>
    <S N='Name'>Quite Imposing Plus 3</S>
    <I N='Version'>1</I>
    </ITEMS>  </DICT>

  <I N='Version'>1</I>
  </ITEMS></DICT>

<DICT N='4'>  <ITEMS>
  <A N='Category'>OneCommand_V1</A>
  <A N='Command'>DefineBleed</A>
  <DICT N='Desc'>    <ITEMS>
    <S N='0'>Range: all odd numbered pages</S>
    <S N='1'>Request: bleed left 0.00, right 0.00, top 0.00, bottom 0.00 points</S>
    <S N='2'>Bleed area is outside visible: no</S>
    </ITEMS>  </DICT>

  <DICT N='Params'>    <ITEMS>
    <F N='BMgn'>0.0000</F>
    <F N='LMgn'>0.0000</F>
    <F N='Margin'>8.5039</F>
    <B N='Outside'>0</B>
    <I N='PosX'>741</I>
    <I N='PosY'>279</I>
    <F N='RMgn'>0.0000</F>
    <A N='Request'>Margin</A>
    <DICT N='Source'>      <ITEMS>
      <DICT N='Range'>        <ITEMS>
        <A N='EvenOdd'>Odd</A>
        <A N='RangeType'>AllDoc</A>
        </ITEMS>      </DICT>

      </ITEMS>    </DICT>

    <F N='TMgn'>0.0000</F>
    </ITEMS>  </DICT>

  <DICT N='Provider'>    <ITEMS>
    <S N='Code'>QITE_QuiteImposingPlus3</S>
    <S N='FullName'>Quite Imposing Plus 3.0f</S>
    <S N='Name'>Quite Imposing Plus 3</S>
    <I N='Version'>1</I>
    </ITEMS>  </DICT>

  <I N='Version'>1</I>
  </ITEMS></DICT>

<DICT N='5'>  <ITEMS>
  <A N='Category'>OneCommand_V1</A>
  <A N='Command'>DefineBleed</A>
  <DICT N='Desc'>    <ITEMS>
    <S N='0'>Range: all even numbered pages</S>
    <S N='1'>Request: bleed left 0.00, right 0.00, top 0.00, bottom 0.00 points</S>
    <S N='2'>Bleed area is outside visible: no</S>
    </ITEMS>  </DICT>

  <DICT N='Params'>    <ITEMS>
    <F N='BMgn'>0.0000</F>
    <F N='LMgn'>0.0000</F>
    <F N='Margin'>0.0000</F>
    <B N='Outside'>0</B>
    <I N='PosX'>741</I>
    <I N='PosY'>279</I>
    <F N='RMgn'>0.0000</F>
    <A N='Request'>Margin</A>
    <DICT N='Source'>      <ITEMS>
      <DICT N='Range'>        <ITEMS>
        <A N='EvenOdd'>Even</A>
        <A N='RangeType'>AllDoc</A>
        </ITEMS>      </DICT>

      </ITEMS>    </DICT>

    <F N='TMgn'>0.0000</F>
    </ITEMS>  </DICT>

  <DICT N='Provider'>    <ITEMS>
    <S N='Code'>QITE_QuiteImposingPlus3</S>
    <S N='FullName'>Quite Imposing Plus 3.0f</S>
    <S N='Name'>Quite Imposing Plus 3</S>
    <I N='Version'>1</I>
    </ITEMS>  </DICT>

  <I N='Version'>1</I>
  </ITEMS></DICT>

<DICT N='6'>  <ITEMS>
  <A N='Category'>OneCommand_V1</A>
  <A N='Command'>Nup</A>
  <DICT N='Desc'>    <ITEMS>
    <S N='0'>Trim unused space from sheets: no</S>
    <S N='1'>Allow pages to be scaled: no</S>
    <S N='2'>Margins: left 14.17, top 14.17, right 14.17, bottom 14.17 points</S>
    <S N='3'>Horizontal spacing (points): 0 </S>
    <S N='4'>Vertical spacing (points): 0 </S>
    <S N='5'>Add frames around each page: no</S>
    <S N='6'>Sheet size: 1.000 x 1.000 inches / 25.4 x 25.4 mm</S>
    <S N='7'>Sheet orientation: wide</S>
    <S N='8'>Layout: rows 1 down, columns 1 across</S>
    <S N='9'>Align: centre, independent</S>
    <S N='10'>Registration colour: Black</S>
    <S N='11'>PDF/X handling: Ignore PDF/X</S>
    <S N='12'>Bleed handling: Use trim box</S>
    <S N='13'>Annotations and form fields: Ignore</S>
    </ITEMS>  </DICT>

  <DICT N='Params'>    <ITEMS>
    <F N='BMgn'>0.0000</F>
    <A N='BleedMode'>Ignore</A>
    <F N='CropDist'>8.5039</F>
    <F N='CropLength'>20.0001</F>
    <B N='CropMarks'>0</B>
    <A N='CropStyle'>Corners</A>
    <F N='CropWidth'>0.2999</F>
    <A N='DoScaling'>ToFit</A>
    <B N='EvenMirrorHorizontal'>1</B>
    <B N='EvenMirrorVertical'>0</B>
    <I N='FitAcross'>1</I>
    <I N='FitDown'>1</I>
    <F N='FixedScale'>0.7000</F>
    <A N='Flatten'>None</A>
    <B N='Frames'>0</B>
    <S N='HSpace'>0 </S>
    <F N='LMgn'>2.8346</F>
    <B N='NewDoc'>0</B>
    <A N='PDFX'>IgnoreAll</A>
    <DICT N='Page'>      <ITEMS>
      <S N='Created'>D:20200808222817</S>
      <F N='Height'>72.0000</F>
      <S N='Name'>SI2</S>
      <A N='Type'>Blank</A>
      <F N='Width'>72.0000</F>
      </ITEMS>    </DICT>

    <A N='PageOrientation'>Tall</A>
    <I N='PosX'>749</I>
    <I N='PosY'>303</I>
    <F N='RMgn'>2.8346</F>
    <A N='RegColour'>Black</A>
    <S N='Requires'>qi3alphabase[QI 3.0/QHI 3.0 alpha]</S>
    <A N='SheetAlign'>C</A>
    <B N='SheetAlignIndependent'>1</B>
    <DICT N='Source'>      <ITEMS>
      <A N='SourceType'>CurrentAVDoc</A>
      </ITEMS>    </DICT>

    <F N='TMgn'>0.0000</F>
    <B N='Trim'>0</B>
    <I N='UIVer'>2</I>
    <B N='UseMgn'>1</B>
    <B N='UseScale'>0</B>
    <S N='VSpace'>0 </S>
    </ITEMS>  </DICT>

  <DICT N='Provider'>    <ITEMS>
    <S N='Code'>QITE_QuiteImposingPlus3</S>
    <S N='FullName'>Quite Imposing Plus 3.0f</S>
    <S N='Name'>Quite Imposing Plus 3</S>
    <I N='Version'>1</I>
    </ITEMS>  </DICT>

  <I N='Version'>1</I>
  </ITEMS></DICT>

<DICT N='7'>  <ITEMS>
  <A N='Category'>OneCommand_V1</A>
  <A N='Command'>Nup</A>
  <DICT N='Desc'>    <ITEMS>
    <S N='0'>Trim unused space from sheets: no</S>
    <S N='1'>Allow pages to be scaled: no</S>
    <S N='2'>Margins: left 0.00, top 0.00, right 0.00, bottom 0.00 points</S>
    <S N='3'>Horizontal spacing (points): 0 </S>
    <S N='4'>Vertical spacing (points): 0 </S>
    <S N='5'>Add frames around each page: no</S>
    <S N='6'>Sheet size: 24.016 x 6.299 inches / 610.0 x 160.0 mm</S>
    <S N='7'>Sheet orientation: best fit</S>
    <S N='8'>Layout: rows 2 down, columns 6 across</S>
    <S N='9'>Align: centre</S>
    </ITEMS>  </DICT>

  <DICT N='Params'>    <ITEMS>
    <F N='BMgn'>0.0000</F>
    <F N='CropDist'>10.0000</F>
    <F N='CropLength'>20.0000</F>
    <B N='CropMarks'>0</B>
    <A N='CropStyle'>Corners</A>
    <F N='CropWidth'>0.3000</F>
    <A N='DoScaling'>ToFit</A>
    <B N='EvenMirrorHorizontal'>0</B>
    <B N='EvenMirrorVertical'>0</B>
    <I N='FitAcross'>6</I>
    <I N='FitDown'>2</I>
    <F N='FixedScale'>0.7000</F>
    <B N='Frames'>0</B>
    <S N='HSpace'>0 </S>
    <F N='LMgn'>0.0000</F>
    <B N='NewDoc'>0</B>
    <DICT N='Page'>      <ITEMS>
      <S N='Created'>D:20250121141519</S>
      <F N='Height'>453.5433</F>
      <A N='Type'>Blank</A>
      <F N='Width'>1729.1339</F>
      </ITEMS>    </DICT>

    <A N='PageOrientation'>Best</A>
    <I N='PosX'>1064</I>
    <I N='PosY'>460</I>
    
    <F N='RMgn'>0.0000</F>
    <A N='SheetAlign'>C</A>
    <B N='SheetAlignIndependent'>0</B>
    <DICT N='Source'>      <ITEMS>
      <A N='SourceType'>CurrentAVDoc</A>
      </ITEMS>    </DICT>

    <F N='TMgn'>0.0000</F>
    <B N='Trim'>0</B>
    <I N='UIVer'>2</I>
    <B N='UseMgn'>1</B>
    <B N='UseScale'>0</B>
    <S N='VSpace'>0 </S>
    </ITEMS>  </DICT>

  <DICT N='Provider'>    <ITEMS>
    <S N='Code'>QITE_QuiteImposingPlus5</S>
    <S N='FullName'>Quite Imposing Plus 5.2</S>
    <S N='Name'>Quite Imposing Plus 5</S>
    <I N='Version'>1</I>
    </ITEMS>  </DICT>

  <I N='Version'>1</I>
  </ITEMS></DICT>

<DICT N='8'>  <ITEMS>
  <A N='Category'>OneCommand_V1</A>
  <A N='Command'>DefineBleed</A>
  <DICT N='Desc'>    <ITEMS>
    <S N='0'>Range: all pages</S>
    <S N='1'>Request: bleed all round 14.17 points</S>
    <S N='2'>Bleed area is outside visible: no</S>
    </ITEMS>  </DICT>

  <DICT N='Params'>    <ITEMS>
    <F N='BMgn'>8.5039</F>
    <F N='LMgn'>8.5039</F>
    <F N='Margin'>14.1732</F>
    <B N='Outside'>0</B>
    <I N='PosX'>741</I>
    <I N='PosY'>279</I>
    <F N='RMgn'>8.5039</F>
    <A N='Request'>Margin</A>
    <DICT N='Source'>      <ITEMS>
      <DICT N='Range'>        <ITEMS>
        <A N='EvenOdd'>Odd</A>
        <A N='RangeType'>AllDoc</A>
        </ITEMS>      </DICT>

      </ITEMS>    </DICT>

    <F N='TMgn'>8.5039</F>
    </ITEMS>  </DICT>

  <DICT N='Provider'>    <ITEMS>
    <S N='Code'>QITE_QuiteImposingPlus3</S>
    <S N='FullName'>Quite Imposing Plus 3.0f</S>
    <S N='Name'>Quite Imposing Plus 3</S>
    <I N='Version'>1</I>
    </ITEMS>  </DICT>

  <I N='Version'>1</I>
  </ITEMS></DICT>

<DICT N='9'>  <ITEMS>
  <A N='Category'>OneCommand_V1</A>
  <A N='Command'>DefineBleed</A>
  <DICT N='Desc'>    <ITEMS>
    <S N='0'>Range: all even numbered pages</S>
    <S N='1'>Request: bleed left 0.00, right 0.00, top 0.00, bottom 0.00 points</S>
    <S N='2'>Bleed area is outside visible: no</S>
    </ITEMS>  </DICT>

  <DICT N='Params'>    <ITEMS>
    <F N='BMgn'>8.5039</F>
    <F N='LMgn'>8.5039</F>
    <F N='Margin'>0.0000</F>
    <B N='Outside'>0</B>
    <I N='PosX'>741</I>
    <I N='PosY'>279</I>
    <F N='RMgn'>8.5039</F>
    <A N='Request'>Margin</A>
    <DICT N='Source'>      <ITEMS>
      <DICT N='Range'>        <ITEMS>
        <A N='EvenOdd'>Even</A>
        <A N='RangeType'>AllDoc</A>
        </ITEMS>      </DICT>

      </ITEMS>    </DICT>

    <F N='TMgn'>8.5039</F>
    </ITEMS>  </DICT>

  <DICT N='Provider'>    <ITEMS>
    <S N='Code'>QITE_QuiteImposingPlus3</S>
    <S N='FullName'>Quite Imposing Plus 3.0f</S>
    <S N='Name'>Quite Imposing Plus 3</S>
    <I N='Version'>1</I>
    </ITEMS>  </DICT>

  <I N='Version'>1</I>
  </ITEMS></DICT>

<A N='Category'>CommandList_V1</A>
<B N='DoPrompt'>0</B>
<S N='Requires'>qi2base</S>
<DICT N='Stats'>  <ITEMS>
  <I N='Count'>2138</I>
  <S N='Created'>D:20130111235145</S>
  <S N='Edited'>D:20250121141712</S>
  <S N='Updated'>D:20150930194956</S>
  </ITEMS></DICT>

<A N='UIMode'>None</A>
</ITEMS>
</QUITEXML>
